myimpute/__init__.py
myimpute/impute.py
myimpute-0.1.1.dist-info/LICENSE
myimpute-0.1.1.dist-info/METADATA
myimpute-0.1.1.dist-info/WHEEL
myimpute-0.1.1.dist-info/top_level.txt
myimpute-0.1.1.dist-info/RECORD
