Metadata-Version: 2.1
Name: myimpute
Version: 0.1.1
Summary: Imputes missing data like a linear equation
Home-page: https://github.com/imjxydhh/MyImputation
Author: Shaobo Zhuang
Author-email: dcbajk@vip.qq.com
License: MIT
Keywords: Imputation,Missing Values,Missing,Linear,Mean
Platform: UNKNOWN
Classifier: Natural Language :: English
Classifier: Programming Language :: Python :: 3.8
Classifier: Programming Language :: Python :: 3.7
Classifier: Programming Language :: Python :: 3.6
Classifier: License :: OSI Approved :: MIT License
Requires-Python: >=3.6
